md2cf/__init__.py
md2cf/__main__.py
md2cf/api.py
md2cf/confluence_renderer.py
md2cf/console_output.py
md2cf/document.py
md2cf/ignored_files.py
md2cf/tui.py
md2cf/upsert.py
md2cf-2.3.0.dist-info/LICENSE
md2cf-2.3.0.dist-info/METADATA
md2cf-2.3.0.dist-info/WHEEL
md2cf-2.3.0.dist-info/entry_points.txt
md2cf-2.3.0.dist-info/top_level.txt
md2cf-2.3.0.dist-info/RECORD
