Metadata-Version: 2.1
Name: md2cf
Version: 2.3.0
Summary: Convert Markdown documents to Confluence
Home-page: https://github.com/iamjackg/md2cf
Author: Jack Gaino
Author-email: md2cf@jackgaino.com
License: MIT
Keywords: markdown confluence
Platform: UNKNOWN
Classifier: Programming Language :: Python :: 3
Classifier: License :: OSI Approved :: MIT License
Classifier: Operating System :: OS Independent
Requires-Python: >=3.7
